pyaida/__init__.py
pyaida/api/__init__.py
pyaida/api/auth/__init__.py
pyaida/api/main.py
pyaida/api/routers/__init__.py
pyaida/api/routers/references.py
pyaida/core/__init__.py
pyaida/core/data/AbstractModel.py
pyaida/core/data/__init__.py
pyaida/core/data/entities/ProjectModel.py
pyaida/core/data/entities/ResourceModel.py
pyaida/core/data/entities/UserActivity.py
pyaida/core/data/entities/__init.__.py
pyaida/core/data/pg/PostgresService.py
pyaida/core/data/pg/__init__.py
pyaida/core/data/sql/__init__.py
pyaida/core/data/sql/helper.py
pyaida/core/lang/FunctionManager.py
pyaida/core/lang/PlanModel.py
pyaida/core/lang/Runner.py
pyaida/core/lang/__init__.py
pyaida/core/lang/functions/Function.py
pyaida/core/lang/functions/__init__.py
pyaida/core/lang/messages/MessageStack.py
pyaida/core/lang/messages/__init__.py
pyaida/core/lang/models/CallingContext.py
pyaida/core/lang/models/__init__.py
pyaida/core/lang/models/claude.py
pyaida/core/lang/models/gpt.py
pyaida/core/parsing/__init__.py
pyaida/core/parsing/email/HtmlEmail.py
pyaida/core/parsing/email/__init__.py
pyaida/core/parsing/openapi.py
pyaida/core/parsing/web/__init__.py
pyaida/core/parsing/web/providers.py
pyaida/core/utils/__init__.py
pyaida/core/utils/dates.py
pyaida/core/utils/env.py
pyaida/core/utils/inspection.py
pyaida/core/utils/schema.py
pyaida-0.1.2.dist-info/METADATA
pyaida-0.1.2.dist-info/WHEEL
pyaida-0.1.2.dist-info/RECORD
